<annotation>
	<folder>YFT</folder>
	<filename>img_04302.jpg</filename>
	<source>
		<database>Source</database>
	</source>
	<size>
		<width>1280</width>
		<height>720</height>
		<depth>3</depth>
	</size>
	<segmented>Unspecified</segmented>
	<object>
		<name>YFT</name>
		<pose>Unspecified</pose>
		<truncated>Unspecified</truncated>
		<difficult>Unspecified</difficult>
		<bndbox>
			<xmin>822.6950354609936</xmin>
			<ymin>395.0354609929081</ymin>
			<xmax>958.8652482269512</xmax>
			<ymax>631.9148936170218</ymax>
		</bndbox>
	</object></annotation>