<annotation>
	<folder>YFT</folder>
	<filename>img_03590.jpg</filename>
	<source>
		<database>Source</database>
	</source>
	<size>
		<width>1280</width>
		<height>720</height>
		<depth>3</depth>
	</size>
	<segmented>Unspecified</segmented>
	<object>
		<name>YFT</name>
		<pose>Unspecified</pose>
		<truncated>Unspecified</truncated>
		<difficult>Unspecified</difficult>
		<bndbox>
			<xmin>225.5319148936172</xmin>
			<ymin>407.09219858156064</ymin>
			<xmax>460.2836879432628</xmax>
			<ymax>505.67375886524866</ymax>
		</bndbox>
	</object></annotation>