<annotation>
	<folder>ALB</folder>
	<filename>img_07172.jpg</filename>
	<source>
		<database>Source</database>
	</source>
	<size>
		<width>1280</width>
		<height>720</height>
		<depth>3</depth>
	</size>
	<segmented>Unspecified</segmented>
	<object>
		<name>ALB</name>
		<pose>Unspecified</pose>
		<truncated>Unspecified</truncated>
		<difficult>Unspecified</difficult>
		<bndbox>
			<xmin>653.854809670782</xmin>
			<ymin>341.59593621399176</ymin>
			<xmax>802.9513888888889</xmax>
			<ymax>498.730066872428</ymax>
		</bndbox>
	</object></annotation>