<annotation>
	<folder>OTHER</folder>
	<filename>img_06149.jpg</filename>
	<source>
		<database>Source</database>
	</source>
	<size>
		<width>1280</width>
		<height>720</height>
		<depth>3</depth>
	</size>
	<segmented>Unspecified</segmented>
	<object>
		<name>OTHER</name>
		<pose>Unspecified</pose>
		<truncated>Unspecified</truncated>
		<difficult>Unspecified</difficult>
		<bndbox>
			<xmin>557.8190231879686</xmin>
			<ymin>400.38227453347423</ymin>
			<xmax>683.06423218148</xmax>
			<ymax>611.1362607514714</ymax>
		</bndbox>
	</object></annotation>