<annotation>
	<folder>ALB</folder>
	<filename>img_07811.jpg</filename>
	<source>
		<database>Source</database>
	</source>
	<size>
		<width>1280</width>
		<height>720</height>
		<depth>3</depth>
	</size>
	<segmented>0</segmented>
	<object>
		<name>ALB</name>
		<pose>Unspecified</pose>
		<truncated>0</truncated>
		<difficult>0</difficult>
		<bndbox>
			<xmin>437.5953130551446</xmin>
			<ymin>385.58016679231935</ymin>
			<xmax>591.7319391367276</xmax>
			<ymax>513.4706181541283</ymax>
		</bndbox>
	</object></annotation>