<annotation>
	<folder>OTHER</folder>
	<filename>img_01080.jpg</filename>
	<source>
		<database>Source</database>
	</source>
	<size>
		<width>1280</width>
		<height>720</height>
		<depth>3</depth>
	</size>
	<segmented>Unspecified</segmented>
	<object>
		<name>OTHER</name>
		<pose>Unspecified</pose>
		<truncated>Unspecified</truncated>
		<difficult>Unspecified</difficult>
		<bndbox>
			<xmin>438.1067350736885</xmin>
			<ymin>404.90920979829997</ymin>
			<xmax>569.8908505608371</xmax>
			<ymax>482.8730949147428</ymax>
		</bndbox>
	</object></annotation>