<annotation>
	<folder>YFT</folder>
	<filename>img_03015.jpg</filename>
	<source>
		<database>Source</database>
	</source>
	<size>
		<width>1280</width>
		<height>974</height>
		<depth>3</depth>
	</size>
	<segmented>0</segmented>
	<object>
		<name>yft</name>
		<pose>Unspecified</pose>
		<truncated>0</truncated>
		<difficult>0</difficult>
		<bndbox>
			<xmin>446.0992907801422</xmin>
			<ymin>437.5886524822699</ymin>
			<xmax>731.2056737588658</xmax>
			<ymax>695.0354609929084</ymax>
		</bndbox>
	</object></annotation>