<annotation>
	<folder>YFT</folder>
	<filename>img_02463.jpg</filename>
	<source>
		<database>Source</database>
	</source>
	<size>
		<width>1280</width>
		<height>720</height>
		<depth>3</depth>
	</size>
	<segmented>Unspecified</segmented>
	<object>
		<name>YFT</name>
		<pose>Unspecified</pose>
		<truncated>Unspecified</truncated>
		<difficult>Unspecified</difficult>
		<bndbox>
			<xmin>821.9858156028375</xmin>
			<ymin>400.70921985815636</ymin>
			<xmax>958.1560283687951</xmax>
			<ymax>628.3687943262416</ymax>
		</bndbox>
	</object></annotation>