<annotation>
	<folder>YFT</folder>
	<filename>img_07427.jpg</filename>
	<source>
		<database>Source</database>
	</source>
	<size>
		<width>1280</width>
		<height>720</height>
		<depth>3</depth>
	</size>
	<segmented>Unspecified</segmented>
	<object>
		<name>YFT</name>
		<pose>Unspecified</pose>
		<truncated>Unspecified</truncated>
		<difficult>Unspecified</difficult>
		<bndbox>
			<xmin>441.84397163120605</xmin>
			<ymin>448.93617021276634</ymin>
			<xmax>620.5673758865254</xmax>
			<ymax>524.8226950354614</ymax>
		</bndbox>
	</object></annotation>