<annotation>
	<folder>ALB</folder>
	<filename>img_06539.jpg</filename>
	<source>
		<database>Source</database>
	</source>
	<size>
		<width>1192</width>
		<height>670</height>
		<depth>3</depth>
	</size>
	<segmented>Unspecified</segmented>
	<object>
		<name>ALB</name>
		<pose>Unspecified</pose>
		<truncated>Unspecified</truncated>
		<difficult>Unspecified</difficult>
		<bndbox>
			<xmin>984.0</xmin>
			<ymin>282.0</ymin>
			<xmax>1036.0</xmax>
			<ymax>379.0</ymax>
		</bndbox>
	</object></annotation>