<annotation>
	<folder>YFT</folder>
	<filename>img_07403.jpg</filename>
	<source>
		<database>Source</database>
	</source>
	<size>
		<width>1280</width>
		<height>720</height>
		<depth>3</depth>
	</size>
	<segmented>0</segmented>
	<object>
		<name>yft</name>
		<pose>Unspecified</pose>
		<truncated>0</truncated>
		<difficult>0</difficult>
		<bndbox>
			<xmin>353.1914893617024</xmin>
			<ymin>401.4184397163124</ymin>
			<xmax>536.8794326241139</xmax>
			<ymax>522.6950354609934</ymax>
		</bndbox>
	</object></annotation>