<annotation>
	<folder>YFT</folder>
	<filename>img_04802.jpg</filename>
	<source>
		<database>Source</database>
	</source>
	<size>
		<width>1280</width>
		<height>720</height>
		<depth>3</depth>
	</size>
	<segmented>0</segmented>
	<object>
		<name>yft</name>
		<pose>Unspecified</pose>
		<truncated>0</truncated>
		<difficult>0</difficult>
		<bndbox>
			<xmin>280.14184397163143</xmin>
			<ymin>412.0567375886528</ymin>
			<xmax>406.38297872340456</xmax>
			<ymax>475.88652482269543</ymax>
		</bndbox>
	</object></annotation>